<?xml version="1.0"?>
<ArrayOfParcel xmlns:xsi="http://www.w3.org/2001/XMLSchema-instance" xmlns:xsd="http://www.w3.org/2001/XMLSchema">
  <Parcel>
    <ID>1000</ID>
    <SenderId>21509585</SenderId>
    <TargetId>73322940</TargetId>
    <Weight>low</Weight>
    <Priority>regular</Priority>
    <Requested>2022-01-10T23:14:29.881146+01:00</Requested>
    <DroneId>0</DroneId>
    <Scheduled xsi:nil="true" />
    <PickedUp xsi:nil="true" />
    <Delivered xsi:nil="true" />
  </Parcel>
  <Parcel>
    <ID>1001</ID>
    <SenderId>82831217</SenderId>
    <TargetId>89493152</TargetId>
    <Weight>heavy</Weight>
    <Priority>regular</Priority>
    <Requested>2022-01-10T23:14:29.886106+01:00</Requested>
    <DroneId>0</DroneId>
    <Scheduled xsi:nil="true" />
    <PickedUp xsi:nil="true" />
    <Delivered xsi:nil="true" />
  </Parcel>
  <Parcel>
    <ID>1002</ID>
    <SenderId>89493152</SenderId>
    <TargetId>21509585</TargetId>
    <Weight>middle</Weight>
    <Priority>regular</Priority>
    <Requested>2022-01-10T23:14:29.8861152+01:00</Requested>
    <DroneId>0</DroneId>
    <Scheduled xsi:nil="true" />
    <PickedUp xsi:nil="true" />
    <Delivered xsi:nil="true" />
  </Parcel>
  <Parcel>
    <ID>1003</ID>
    <SenderId>73322940</SenderId>
    <TargetId>68481011</TargetId>
    <Weight>low</Weight>
    <Priority>emergency</Priority>
    <Requested>2022-01-10T23:14:29.8861166+01:00</Requested>
    <DroneId>0</DroneId>
    <Scheduled xsi:nil="true" />
    <PickedUp xsi:nil="true" />
    <Delivered xsi:nil="true" />
  </Parcel>
  <Parcel>
    <ID>1004</ID>
    <SenderId>82533534</SenderId>
    <TargetId>69776410</TargetId>
    <Weight>heavy</Weight>
    <Priority>regular</Priority>
    <Requested>2022-01-10T23:14:29.8861179+01:00</Requested>
    <DroneId>0</DroneId>
    <Scheduled xsi:nil="true" />
    <PickedUp xsi:nil="true" />
    <Delivered xsi:nil="true" />
  </Parcel>
  <Parcel>
    <ID>1005</ID>
    <SenderId>73801063</SenderId>
    <TargetId>73322940</TargetId>
    <Weight>low</Weight>
    <Priority>emergency</Priority>
    <Requested>2022-01-10T23:14:29.8861199+01:00</Requested>
    <DroneId>0</DroneId>
    <Scheduled xsi:nil="true" />
    <PickedUp xsi:nil="true" />
    <Delivered xsi:nil="true" />
  </Parcel>
  <Parcel>
    <ID>1006</ID>
    <SenderId>89493152</SenderId>
    <TargetId>68481011</TargetId>
    <Weight>low</Weight>
    <Priority>emergency</Priority>
    <Requested>2022-01-10T23:14:29.8861209+01:00</Requested>
    <DroneId>0</DroneId>
    <Scheduled xsi:nil="true" />
    <PickedUp xsi:nil="true" />
    <Delivered xsi:nil="true" />
  </Parcel>
  <Parcel>
    <ID>1007</ID>
    <SenderId>82831217</SenderId>
    <TargetId>69776410</TargetId>
    <Weight>low</Weight>
    <Priority>emergency</Priority>
    <Requested>2022-01-10T23:14:29.8861219+01:00</Requested>
    <DroneId>0</DroneId>
    <Scheduled xsi:nil="true" />
    <PickedUp xsi:nil="true" />
    <Delivered xsi:nil="true" />
  </Parcel>
  <Parcel>
    <ID>1008</ID>
    <SenderId>82533534</SenderId>
    <TargetId>17387373</TargetId>
    <Weight>middle</Weight>
    <Priority>regular</Priority>
    <Requested>2022-01-10T23:14:29.8861231+01:00</Requested>
    <DroneId>0</DroneId>
    <Scheduled xsi:nil="true" />
    <PickedUp xsi:nil="true" />
    <Delivered xsi:nil="true" />
  </Parcel>
  <Parcel>
    <ID>1009</ID>
    <SenderId>68481011</SenderId>
    <TargetId>73801063</TargetId>
    <Weight>low</Weight>
    <Priority>emergency</Priority>
    <Requested>2022-01-10T23:14:29.8861244+01:00</Requested>
    <DroneId>0</DroneId>
    <Scheduled xsi:nil="true" />
    <PickedUp xsi:nil="true" />
    <Delivered xsi:nil="true" />
  </Parcel>
</ArrayOfParcel>